rlskyjo/__init__.py
rlskyjo/utils.py
rlskyjo/environment/__init__.py
rlskyjo/environment/skyjo_env.py
rlskyjo/environment/vanilla_env_example.py
rlskyjo/game/__init__.py
rlskyjo/game/sample_game.py
rlskyjo/game/skyjo.py
rlskyjo/models/__init__.py
rlskyjo/models/action_mask_model.py
rlskyjo/models/random_admissible_policy.py
rlskyjo/models/train_model_simple_rllib.py
rlskyjo-1.0.0.dist-info/LICENSE
rlskyjo-1.0.0.dist-info/METADATA
rlskyjo-1.0.0.dist-info/WHEEL
rlskyjo-1.0.0.dist-info/top_level.txt
rlskyjo-1.0.0.dist-info/RECORD
