Metadata-Version: 2.1
Name: rlskyjo
Version: 1.0.0
Summary: Multi-Agent Reinforcement Learning Environment for the card game SkyJo, compatible with PettingZoo and RLLIB
Home-page: https://github.com/michaelfeil/skyjo_rl
Author: Michael Feil
License: MIT
Project-URL: Bug Tracker, https://github.com/michaelfeil/skyjo_rl/issues
Platform: UNKNOWN
Classifier: Programming Language :: Python :: 3
Classifier: License :: OSI Approved :: MIT License
Classifier: Operating System :: POSIX :: Linux
License-File: LICENSE
Requires-Dist: gym
Requires-Dist: numba
Requires-Dist: numpy
Requires-Dist: PettingZoo
Requires-Dist: ray[tune]
Requires-Dist: ray[rllib]
Requires-Dist: setuptools
Requires-Dist: torch
